README.rst
setup.py
solpy/StationsMeta.csv
solpy/__init__.py
solpy/collectors.py
solpy/design.py
solpy/ee.py
solpy/enphase.py
solpy/epw.py
solpy/epw_thermal.py
solpy/epwurls.csv
solpy/expedite.py
solpy/fisheye.py
solpy/forecast.py
solpy/geo.py
solpy/inverters.py
solpy/irradiation.py
solpy/modules.py
solpy/nec.py
solpy/noaa.py
solpy/nsrdb.py
solpy/pathfinder.py
solpy/pmodel.py
solpy/pv.py
solpy/si.json
solpy/site_analysis.py
solpy/solar_fun.py
solpy/sp.json
solpy/summary.py
solpy/thermal.py
solpy/tl.json
solpy/tmy3.py
solpy/tmy3urls.csv
solpy/tools.py
solpy/vd.py
solpy/zipcode.csv
solpy.egg-info/PKG-INFO
solpy.egg-info/SOURCES.txt
solpy.egg-info/dependency_links.txt
solpy.egg-info/requires.txt
solpy.egg-info/top_level.txt
tests/__init__.py
tests/unit.py