Metadata-Version: 1.1
Name: solpy
Version: 0.15.4.9
Summary: Solar Performance and Design library
Home-page: https://github.com/nrcharles/solpy
Author: Nathan Charles
Author-email: ncharles@gmail.com
License: LGPL
Keywords: solar pv
Platform: UNKNOWN
Classifier: Development Status :: 4 - Beta
Classifier: License :: OSI Approved :: GNU Library or Lesser General Public License (LGPL)
